<?xml version="1.0" encoding="utf-8"?>

<window>		
	<back_video x="0" y="0" width="1024" height="430">
		<texture x="0" y="0" width="1024" height="430">ui\ui_mm_window_back_crop</texture>
	</back_video>

	<background x="0" y="0" width="1024" height="768">
		<texture>ui\ui_static_mm_back_03</texture>
	</background>

	<rug_video x="275" y="425" width="128" height="256">
		<texture>ui\ui_mm_rug02</texture>
	</rug_video>

	<main_dialog>
		<dialog x="415" y="168" width="548" height="461">
			<texture>ui_menu_options_dlg</texture>
		</dialog>
		<cap_options x="45" y="3" width="378" height="33">
			<text font="graffiti22" r="215" g="195" b="170">ui_mm_options</text>
		</cap_options>
		<btn_accept x="219" y="426" width="157" height="48">
			<text font="graffiti19" align="c">ui_mm_apply</text>
			<texture>ui_button_main02</texture>
			<text_color>
				<e r="227" g="199" b="178"/>				
				<t r="180" g="153" b="155"/>				
				<d r="106" g="95" b="91"/>							
				<h r="0" g="0" b="0"/>
			</text_color>
		</btn_accept>
		<btn_cancel x="375" y="426" width="157" height="48">
			<text font="graffiti19" align="c">ui_mm_cancel</text>
			<texture>ui_button_main03</texture>
			<text_color>
				<e r="227" g="199" b="178"/>				
				<t r1="180" g="153" b="155"/>				
				<d r="106" g="95" b="91"/>							
				<h r="0" g="0" b="0"/>
			</text_color>
		</btn_cancel>
		<tab x="55" y="48" width="461" height="26">
			<button x="0" y="0" width="116" height="26">
				<texture_offset x="0" y="-7"/>
				<texture>ui_button_tablist</texture>
				<text font="graffiti19" align="c">ui_mm_video</text>				
				<text_color>
					<e r="106" g="95" b="91"/>
					<t r="227" g="199" b="178"/>
					<h r="180" g="153" b="155"/>
				</text_color>
			</button>
			<button x="116" y="0" width="116" height="26">
				<texture_offset x="0" y="-7"/>
				<texture>ui_button_tablist</texture>
				<text font="graffiti19" align="c">ui_mm_sound</text>
				<text_color>
					<e r="106" g="95" b="91"/>
					<t r="227" g="199" b="178"/>
					<h r="180" g="153" b="155"/>
				</text_color>
			</button>
			<button x="232" y="0" width="116" height="26">
				<texture_offset x="0" y="-7"/>
				<texture>ui_button_tablist</texture>
				<text font="graffiti19" align="c">ui_mm_gameplay</text>
				<text_color>
					<e r="106" g="95" b="91"/>
					<t r="227" g="199" b="178"/>
					<h r="180" g="153" b="155"/>
				</text_color>
			</button>
			<button x="348" y="0" width="116" height="26">
				<texture_offset x="0" y="-7"/>
				<texture>ui_button_tablist</texture>
				<text font="graffiti19" align="c">ui_mm_controls</text>
				<text_color>
					<e r="106" g="95" b="91"/>
					<t r="227" g="199" b="178"/>
					<h r="180" g="153" b="155"/>
				</text_color>
			</button>
		</tab>
	</main_dialog>
	<tab_video>
		<cap_preset x="20" y="20" width="143" height="21">
			<text font="letterica16" r="215" g="195" b="170">ui_mm_quality_presets</text>	
			<hint x="0" y="0" changeVisability="1">
				<text align="l" font="letterica16">ui_mm_quality_presets_hint</text>
				<hint_texture a="190" r="0" g="0" b="0">ui\ui_console</hint_texture>
				<text_color>
					<e r="0" g="0" b="0" a="0"/> 		<!-- Hidded -->
					<h r="215" g="195" b="170" a="160"/> 	<!-- Enabled -->
				</text_color>
			</hint>			
		</cap_preset>
		<list_presets x="164" y="20" width="291" height="21" list_length="7">
			<options_item entry="_preset" group="mm_opt_video_preset"/>
			<text_color>
				<e r="216" g="186" b="140"/> 
				<d r="227" g="199" b="178"/>
			</text_color>
			<list_font_s r="240" g="217" b="182"/>
			<list_font	 r="216" g="186" b="140" font="letterica16"/>
		</list_presets>

		<cap_effpreset x="20" y="50" width="143" height="21">
			<text font="letterica16" r="215" g="195" b="170">ui_mm_effects_presets</text>
			<hint x="0" y="0" changeVisability="1">
				<text align="l" font="letterica16">ui_mm_effects_presets_hint</text>
				<hint_texture a="190" r="0" g="0" b="0">ui\ui_console</hint_texture>
				<text_color>
					<e r="0" g="0" b="0" a="0"/> 		<!-- Hidded -->
					<h r="215" g="195" b="170" a="160"/> 	<!-- Enabled -->
				</text_color>
			</hint>				
		</cap_effpreset>
		<list_effpresets x="164" y="50" width="291" height="21" list_length="3">
			<options_item entry="eff_preset" group="mm_opt_video"/>
			<text_color>
				<e r="216" g="186" b="140"/> 
				<d r="227" g="199" b="178"/>
			</text_color>
			<list_font_s r="240" g="217" b="182"/>
			<list_font	 r="216" g="186" b="140" font="letterica16"/>
		</list_effpresets>

		<cap_resolution x="20" y="80" width="143" height="21">
			<text font="letterica16" r="215" g="195" b="170">ui_mm_resolution</text>
		</cap_resolution>
		<list_resolution x="164" y="80" width="291" height="21" always_show_scroll="1" list_length="11">
			<options_item entry="vid_mode" group="mm_opt_video"/>
			<text_color>
				<e r="216" g="186" b="140"/>
				<d r="227" g="199" b="178"/>
			</text_color>
			<list_font_s r="240" g="217" b="182"/>
			<list_font	 r="216" g="186" b="140" font="letterica16"/>
		</list_resolution>

		<cap_gamma x="20" y="110" width="143" height="21">
			<text font="letterica16" r="215" g="195" b="170">ui_mm_gamma</text>
		</cap_gamma>
		<track_gamma x="164" y="110" width="291" height="21" step="0.001">
			<options_item entry="rs_c_gamma" group="mm_opt_video"/>
		</track_gamma>

		<cap_contrast x="20" y="140" width="143" height="21">
			<text font="letterica16" r="215" g="195" b="170">ui_mm_contrast</text>
		</cap_contrast>
		<track_contrast x="164" y="140" width="291" height="21" step="0.001">
			<options_item entry="rs_c_contrast" group="mm_opt_video"/>
		</track_contrast>

		<cap_brightness x="20" y="170" width="143" height="21">
			<text font="letterica16" r="215" g="195" b="170">ui_mm_brightness</text>
		</cap_brightness>
		<track_brightness x="164" y="170" width="291" height="21" step="0.001">
			<options_item entry="rs_c_brightness" group="mm_opt_video"/>
		</track_brightness>

		<cap_fov x="20" y="200" width="143" height="21">
			<text font="letterica16" r="215" g="195" b="170">ui_mm_fov</text>
		</cap_fov>
		<track_fov x="164" y="200" width="291" height="21" step="0.001">
			<options_item entry="fov" group="mm_opt_video"/>
		</track_fov>

		<cap_fullscreen x="20" y="230" width="143" height="21">
			<text font="letterica16" r="215" g="195" b="170">ui_mm_fullscreen</text>
		</cap_fullscreen>
		<check_fullscreen x="164" y="230" width="30" height="21">
			<options_item entry="rs_fullscreen" group="mm_opt_video"/>	
		</check_fullscreen>

		<cap_vsync x="20" y="260" width="143" height="21">
			<text font="letterica16" r="215" g="195" b="170">ui_mm_vsync</text>
			<hint x="0" y="0" changeVisability="1">
				<text align="l" font="letterica16">ui_mm_vsync_hint</text>
				<hint_texture a="190" r="0" g="0" b="0">ui\ui_console</hint_texture>
				<text_color>
					<e r="0" g="0" b="0" a="0"/> 		<!-- Hidded -->
					<h r="215" g="195" b="170" a="160"/> 	<!-- Enabled -->
				</text_color>
			</hint>
		</cap_vsync>
		<check_vsync x="164" y="260" width="30" height="21">
			<options_item entry="rs_v_sync" group="mm_opt_video"/>	
			<hint x="0" y="0" changeVisability="1">
				<text align="l" font="letterica16">ui_mm_vsync_hint</text>
				<hint_texture a="190" r="0" g="0" b="0">ui\ui_console</hint_texture>
				<text_color>
					<e r="0" g="0" b="0" a="0"/> 		<!-- Hidded -->
					<h r="215" g="195" b="170" a="160"/> 	<!-- Enabled -->
				</text_color>
			</hint>
		</check_vsync>
		
		<btn_default_set x="225" y="325" width="111" height="29">
			<text align="c" font="letterica16" r="227" g="199" b="178">ui_mm_default</text>	
			<texture>ui_button_ordinary</texture>			
		</btn_default_set>

		<btn_advanced x="342" y="325" width="111" height="29">
			<text align="c" font="letterica16" r="227" g="199" b="178">ui_mm_advanced</text>	
			<texture>ui_button_ordinary</texture>			
		</btn_advanced>
		
	</tab_video>

	<video_adv>
		<scroll_v	x="0" y="10" width="457" height="313" 
					right_ident="0" left_ident="0" top_indent="0" bottom_indent="0" 
					vert_interval="0" always_show_scroll="0" flip_vert="1"/>

		<templ_item width="450" height="30"/>

		<cap_opt_desc_main x="280" y="0" width="143" height="21">
			<text font="letterica16" r="215" g="195" b="170">ui_mm_opt_desc_main</text>
		</cap_opt_desc_main>

		<cap_opt_desc_relief x="280" y="0" width="143" height="21">
			<text font="letterica16" r="215" g="195" b="170">ui_mm_opt_desc_relief</text>
		</cap_opt_desc_relief>

		<cap_opt_desc_postprocess x="280" y="0" width="143" height="21">
			<text font="letterica16" r="215" g="195" b="170">ui_mm_opt_desc_postprocess</text>
		</cap_opt_desc_postprocess>

		<cap_opt_desc_lighting x="280" y="0" width="143" height="21">
			<text font="letterica16" r="215" g="195" b="170">ui_mm_opt_desc_lighting</text>
		</cap_opt_desc_lighting>

		<cap_r_debug x="20" y="0" width="143" height="21">
			<text font="letterica16" r="215" g="195" b="170">ui_mm_r_debug</text>
		</cap_r_debug>
		<list_r_debug x="194" y="0" width="245" height="21" list_length="10">
			<options_item entry="r_debug" group="mm_opt_video"/>
			<text_color>
				<e r="216" g="186" b="140"/>
				<d r="227" g="199" b="178"/>
			</text_color>
			<list_font_s r="240" g="217" b="182"/>
			<list_font	 r="216" g="186" b="140" font="letterica16"/>
		</list_r_debug>

		<cap_vis_dist x="20" y="0" width="143" height="21">
			<text font="letterica16" r="215" g="195" b="170">ui_mm_vis_distance</text>
		</cap_vis_dist>
		<track_vis_dist x="194" y="0" width="245" height="21" step="0.1">
			<options_item entry="rs_vis_distance" group="mm_opt_video_adv"/>
		</track_vis_dist>
		
		<cap_geometry_lod x="20" y="0" width="143" height="21">
			<text font="letterica16" r="215" g="195" b="170">ui_mm_geometry_lod</text>
		</cap_geometry_lod>
		<track_geometry_lod x="194" y="0" width="245" height="21" step="0.1">
			<options_item entry="r_geometry_lod" group="mm_opt_video_adv"/>
		</track_geometry_lod>
		
		<cap_detalization_distance x="20" y="0" width="143" height="21">
			<text font="letterica16" r="215" g="195" b="170">ui_mm_detalization_distance</text>
		</cap_detalization_distance>
		<track_detalization_distance x="194" y="0" width="245" height="21" invert="0" step="0.1" is_integer="0">
			<options_item entry="r_detalization_distance" group="mm_opt_video_adv"/>
		</track_detalization_distance>

		<cap_detail_density x="20" y="0" width="143" height="21">
			<text font="letterica16" r="215" g="195" b="170">ui_mm_detail_density</text>
		</cap_detail_density>
		<track_detail_density x="194" y="0" width="245" height="21" invert="1" step="0.02">
			<options_item entry="r_detail_density" group="mm_opt_video_adv"/>
		</track_detail_density>

		<cap_texture_lod x="20" y="0" width="143" height="21" >
			<text font="letterica16" r="215" g="195" b="170">ui_mm_texture_quality</text>
		</cap_texture_lod>
		<track_texture_lod x="194" y="0" width="245" height="21" invert="1" step="1" is_integer="1">
			<options_item entry="texture_lod" group="mm_opt_video_adv"/>
		</track_texture_lod>
	
		<cap_r_anti_aliasing x="20" y="0" width="143" height="21">
			<text font="letterica16" r="215" g="195" b="170">ui_mm_r_anti_aliasing</text>
			<hint x="0" y="0" changeVisability="1">
				<text align="l" font="letterica16">ui_mm_r_anti_aliasing_hint</text>
				<hint_texture a="190" r="0" g="0" b="0">ui\ui_console</hint_texture>
				<text_color>
					<e r="0" g="0" b="0" a="0"/> 		<!-- Hidded -->
					<h r="215" g="195" b="170" a="160"/> 	<!-- Enabled -->
				</text_color>
			</hint>
		</cap_r_anti_aliasing>
		<check_r_anti_aliasing x="194" y="0" width="30" height="21">
			<options_item entry="r_anti_aliasing" group="mm_opt_video_adv"/>
			<hint x="0" y="0" changeVisability="1">
				<text align="l" font="letterica16">ui_mm_r_anti_aliasing_hint</text>
				<hint_texture a="190" r="0" g="0" b="0">ui\ui_console</hint_texture>
				<text_color>
					<e r="0" g="0" b="0" a="0"/> 		<!-- Hidded -->
					<h r="215" g="195" b="170" a="160"/> 	<!-- Enabled -->
				</text_color>
			</hint>
		</check_r_anti_aliasing>

		<cap_r_anti_aliasing_alpha_test x="20" y="0" width="143" height="21">
			<text font="letterica16" r="215" g="195" b="170">ui_mm_r_anti_aliasing_alpha_test</text>
			<hint x="0" y="0" changeVisability="1">
				<text align="l" font="letterica16">ui_mm_r_anti_aliasing_alpha_test_hint</text>
				<hint_texture a="190" r="0" g="0" b="0">ui\ui_console</hint_texture>
				<text_color>
					<e r="0" g="0" b="0" a="0"/> 		<!-- Hidded -->
					<h r="215" g="195" b="170" a="160"/> 	<!-- Enabled -->
				</text_color>
			</hint>
		</cap_r_anti_aliasing_alpha_test>
		<check_r_anti_aliasing_alpha_test x="194" y="0" width="30" height="21">
			<options_item entry="r_anti_aliasing_alpha_test" group="mm_opt_video_adv"/>
			<hint x="0" y="0" changeVisability="1">
				<text align="l" font="letterica16">ui_mm_r_anti_aliasing_alpha_test_hint</text>
				<hint_texture a="190" r="0" g="0" b="0">ui\ui_console</hint_texture>
				<text_color>
					<e r="0" g="0" b="0" a="0"/> 		<!-- Hidded -->
					<h r="215" g="195" b="170" a="160"/> 	<!-- Enabled -->
				</text_color>
			</hint>
		</check_r_anti_aliasing_alpha_test>

		<cap_r_chromatic_abberation x="20" y="0" width="143" height="21">
			<text font="letterica16" r="215" g="195" b="170">ui_mm_r_chromatic_abberation</text>
			<hint x="0" y="0" changeVisability="1">
				<text align="l" font="letterica16">ui_mm_r_chromatic_abberation_hint</text>
				<hint_texture a="190" r="0" g="0" b="0">ui\ui_console</hint_texture>
				<text_color>
					<e r="0" g="0" b="0" a="0"/> 		<!-- Hidded -->
					<h r="215" g="195" b="170" a="160"/> 	<!-- Enabled -->
				</text_color>
			</hint>
		</cap_r_chromatic_abberation>
		<check_r_chromatic_abberation x="194" y="0" width="30" height="21">
			<options_item entry="r_chromatic_abberation" group="mm_opt_video_adv"/>
			<hint x="0" y="0" changeVisability="1">
				<text align="l" font="letterica16">ui_mm_r_chromatic_abberation_hint</text>
				<hint_texture a="190" r="0" g="0" b="0">ui\ui_console</hint_texture>
				<text_color>
					<e r="0" g="0" b="0" a="0"/> 		<!-- Hidded -->
					<h r="215" g="195" b="170" a="160"/> 	<!-- Enabled -->
				</text_color>
			</hint>
		</check_r_chromatic_abberation>

		<cap_r_vignette_mode x="20" y="0" width="143" height="21">
			<text font="letterica16" r="215" g="195" b="170">ui_mm_r_vignette_mode</text>
			<hint x="0" y="0" changeVisability="1">
				<text align="l" font="letterica16">ui_mm_r_vignette_mode_hint</text>
				<hint_texture a="190" r="0" g="0" b="0">ui\ui_console</hint_texture>
				<text_color>
					<e r="0" g="0" b="0" a="0"/> 		<!-- Hidded -->
					<h r="215" g="195" b="170" a="160"/> 	<!-- Enabled -->
				</text_color>
			</hint>
		</cap_r_vignette_mode>
		<list_r_vignette_mode x="194" y="0" width="245" height="21" list_length="3">
			<options_item entry="r_vignette_mode" group="mm_opt_video_adv"/>
			<text_color>
				<e r="216" g="186" b="140"/>
				<d r="227" g="199" b="178"/>
			</text_color>
			<list_font_s r="240" g="217" b="182"/>
			<list_font	 r="216" g="186" b="140" font="letterica16"/>
		</list_r_vignette_mode>

		<cap_r_sepia x="20" y="0" width="143" height="21">
			<text font="letterica16" r="215" g="195" b="170">ui_mm_r_sepia</text>
			<hint x="0" y="0" changeVisability="1">
				<text align="l" font="letterica16">ui_mm_r_sepia_hint</text>
				<hint_texture a="190" r="0" g="0" b="0">ui\ui_console</hint_texture>
				<text_color>
					<e r="0" g="0" b="0" a="0"/> 		<!-- Hidded -->
					<h r="215" g="195" b="170" a="160"/> 	<!-- Enabled -->
				</text_color>
			</hint>
		</cap_r_sepia>
		<check_r_sepia x="194" y="0" width="30" height="21">
			<options_item entry="r_sepia" group="mm_opt_video_adv"/>
			<hint x="0" y="0" changeVisability="1">
				<text align="l" font="letterica16">ui_mm_r_sepia_hint</text>
				<hint_texture a="190" r="0" g="0" b="0">ui\ui_console</hint_texture>
				<text_color>
					<e r="0" g="0" b="0" a="0"/> 		<!-- Hidded -->
					<h r="215" g="195" b="170" a="160"/> 	<!-- Enabled -->
				</text_color>
			</hint>
		</check_r_sepia>

		<cap_r_bloom x="20" y="0" width="143" height="21">
			<text font="letterica16" r="215" g="195" b="170">ui_mm_r_bloom</text>
			<hint x="0" y="0" changeVisability="1">
				<text align="l" font="letterica16">ui_mm_r_bloom_hint</text>
				<hint_texture a="190" r="0" g="0" b="0">ui\ui_console</hint_texture>
				<text_color>
					<e r="0" g="0" b="0" a="0"/> 		<!-- Hidded -->
					<h r="215" g="195" b="170" a="160"/> 	<!-- Enabled -->
				</text_color>
			</hint>
		</cap_r_bloom>
		<check_r_bloom x="194" y="0" width="30" height="21">
			<options_item entry="r_bloom" group="mm_opt_video_adv"/>
			<hint x="0" y="0" changeVisability="1">
				<text align="l" font="letterica16">ui_mm_r_bloom_hint</text>
				<hint_texture a="190" r="0" g="0" b="0">ui\ui_console</hint_texture>
				<text_color>
					<e r="0" g="0" b="0" a="0"/> 		<!-- Hidded -->
					<h r="215" g="195" b="170" a="160"/> 	<!-- Enabled -->
				</text_color>
			</hint>
		</check_r_bloom>

		<cap_r_bloom_quality x="20" y="0" width="143" height="21">
			<text font="letterica16" r="215" g="195" b="170">ui_mm_r_bloom_quality</text>
		</cap_r_bloom_quality>
		<list_r_bloom_quality x="194" y="0" width="245" height="21" list_length="4">
			<options_item entry="r_bloom_quality" group="mm_opt_video_adv"/>
			<text_color>
				<e r="216" g="186" b="140"/>
				<d r="227" g="199" b="178"/>
			</text_color>
			<list_font_s r="240" g="217" b="182"/>
			<list_font	 r="216" g="186" b="140" font="letterica16"/>
		</list_r_bloom_quality>

		<cap_r_lens_flares x="20" y="0" width="143" height="21">
			<text font="letterica16" r="215" g="195" b="170">ui_mm_r_lens_flares</text>
			<hint x="0" y="0" changeVisability="1">
				<text align="l" font="letterica16">ui_mm_r_lens_flares_hint</text>
				<hint_texture a="190" r="0" g="0" b="0">ui\ui_console</hint_texture>
				<text_color>
					<e r="0" g="0" b="0" a="0"/> 		<!-- Hidded -->
					<h r="215" g="195" b="170" a="160"/> 	<!-- Enabled -->
				</text_color>
			</hint>
		</cap_r_lens_flares>
		<check_r_lens_flares x="194" y="0" width="30" height="21">
			<options_item entry="r_lens_flares" group="mm_opt_video_adv"/>
			<hint x="0" y="0" changeVisability="1">
				<text align="l" font="letterica16">ui_mm_r_lens_flares_hint</text>
				<hint_texture a="190" r="0" g="0" b="0">ui\ui_console</hint_texture>
				<text_color>
					<e r="0" g="0" b="0" a="0"/> 		<!-- Hidded -->
					<h r="215" g="195" b="170" a="160"/> 	<!-- Enabled -->
				</text_color>
			</hint>
		</check_r_lens_flares>

		<cap_aniso x="20" y="0" width="143" height="21">
			<text font="letterica16" r="215" g="195" b="170">ui_mm_anisotropic</text>
			<hint x="0" y="0" changeVisability="1">
				<text align="l" font="letterica16">ui_mm_anisotropic_hint</text>
				<hint_texture a="190" r="0" g="0" b="0">ui\ui_console</hint_texture>
				<text_color>
					<e r="0" g="0" b="0" a="0"/> 		<!-- Hidded -->
					<h r="215" g="195" b="170" a="160"/> 	<!-- Enabled -->
				</text_color>
			</hint>
		</cap_aniso>
		<track_aniso x="194" y="0" width="245" height="21" step="1" is_integer="1">
			<options_item entry="r_tf_aniso" group="mm_opt_video_adv"/>
			<hint x="0" y="0" changeVisability="1">
				<text align="l" font="letterica16">ui_mm_anisotropic_hint</text>
				<hint_texture a="190" r="0" g="0" b="0">ui\ui_console</hint_texture>
				<text_color>
					<e r="0" g="0" b="0" a="0"/> 		<!-- Hidded -->
					<h r="215" g="195" b="170" a="160"/> 	<!-- Enabled -->
				</text_color>
			</hint>
		</track_aniso>

		<cap_r_dof x="20" y="0" width="143" height="21">
			<text font="letterica16" r="215" g="195" b="170">ui_mm_r_dof</text>
			<hint x="0" y="0" changeVisability="1">
				<text align="l" font="letterica16">ui_mm_r_dof_hint</text>
				<hint_texture a="190" r="0" g="0" b="0">ui\ui_console</hint_texture>
				<text_color>
					<e r="0" g="0" b="0" a="0"/> 		<!-- Hidded -->
					<h r="215" g="195" b="170" a="160"/> 	<!-- Enabled -->
				</text_color>
			</hint>
		</cap_r_dof>
		<check_r_dof x="194" y="0" width="243" height="21">
			<options_item entry="r_dof_enabled" group="mm_opt_video_adv"/>
			<hint x="0" y="0" changeVisability="1">
				<text align="l" font="letterica16">ui_mm_r_dof_hint</text>
				<hint_texture a="190" r="0" g="0" b="0">ui\ui_console</hint_texture>
				<text_color>
					<e r="0" g="0" b="0" a="0"/> 		<!-- Hidded -->
					<h r="215" g="195" b="170" a="160"/> 	<!-- Enabled -->
				</text_color>
			</hint>
		</check_r_dof>

		<cap_r_dof_quality x="20" y="0" width="143" height="21">
			<text font="letterica16" r="215" g="195" b="170">ui_mm_r_dof_quality</text>
		</cap_r_dof_quality>
		<list_r_dof_quality x="194" y="0" width="245" height="21" list_length="4">
			<options_item entry="r_dof_quality" group="mm_opt_video_adv"/>
			<text_color>
				<e r="216" g="186" b="140"/>
				<d r="227" g="199" b="178"/>
			</text_color>
			<list_font_s r="240" g="217" b="182"/>
			<list_font	 r="216" g="186" b="140" font="letterica16"/>
		</list_r_dof_quality>

		<cap_r_mblur_enabled x="20" y="0" width="143" height="21">
			<text font="letterica16" r="215" g="195" b="170">ui_mm_r_mblur</text>
			<hint x="0" y="0" changeVisability="1">
				<text align="l" font="letterica16">ui_mm_r_mblur_hint</text>
				<hint_texture a="190" r="0" g="0" b="0">ui\ui_console</hint_texture>
				<text_color>
					<e r="0" g="0" b="0" a="0"/> 		<!-- Hidded -->
					<h r="215" g="195" b="170" a="160"/> 	<!-- Enabled -->
				</text_color>
			</hint>
		</cap_r_mblur_enabled>
		<check_r_mblur_enabled x="194" y="0" width="243" height="21">
			<options_item entry="r_mblur_enabled" group="mm_opt_video_adv"/>
		</check_r_mblur_enabled>

		<cap_r_mblur_power x="20" y="0" width="143" height="21">
			<text font="letterica16" r="215" g="195" b="170">ui_mm_r_mblur_scale</text>
		</cap_r_mblur_power>
		<track_r_mblur_power x="194" y="0" width="245" height="21" step="0.001">
			<options_item entry="r_mblur_power" group="mm_opt_video_adv"/>
		</track_r_mblur_power>

		<cap_r_barrel_blur x="20" y="0" width="143" height="21">
			<text font="letterica16" r="215" g="195" b="170">ui_mm_r_barrel_blur</text>
		</cap_r_barrel_blur>
		<check_r_barrel_blur x="194" y="0" width="243" height="21">
			<options_item entry="r_barrel_blur" group="mm_opt_video_adv"/>
		</check_r_barrel_blur>

		<cap_r_cas x="20" y="0" width="143" height="21">
			<text font="letterica16" r="255" g="0" b="0">ui_mm_r_cas</text>
			<hint x="0" y="0" changeVisability="1">
				<text align="l" font="letterica16">ui_mm_r_cas_hint</text>
				<hint_texture a="190" r="0" g="0" b="0">ui\ui_console</hint_texture>
				<text_color>
					<e r="0" g="0" b="0" a="0"/> 		<!-- Hidded -->
					<h r="215" g="195" b="170" a="160"/> 	<!-- Enabled -->
				</text_color>
			</hint>
		</cap_r_cas>
		<check_r_cas x="194" y="0" width="243" height="21">
			<options_item entry="r_cas_enabled" group="mm_opt_video_adv"/>
			<hint x="0" y="0" changeVisability="1">
				<text align="l" font="letterica16">ui_mm_r_cas_hint</text>
				<hint_texture a="190" r="0" g="0" b="0">ui\ui_console</hint_texture>
				<text_color>
					<e r="0" g="0" b="0" a="0"/> 		<!-- Hidded -->
					<h r="215" g="195" b="170" a="160"/> 	<!-- Enabled -->
				</text_color>
			</hint>
		</check_r_cas>

		<cap_r_cas_contrast x="20" y="0" width="143" height="21">
			<text font="letterica16" r="215" g="195" b="170">ui_mm_r_cas_contrast</text>
		</cap_r_cas_contrast>
		<track_r_cas_contrast x="194" y="0" width="245" height="21" step="0.001">
			<options_item entry="r_cas_contrast" group="mm_opt_video_adv"/>
		</track_r_cas_contrast>

		<cap_r_cas_sharpening x="20" y="0" width="143" height="21">
			<text font="letterica16" r="215" g="195" b="170">ui_mm_r_cas_sharpening</text>
		</cap_r_cas_sharpening>
		<track_r_cas_sharpening x="194" y="0" width="245" height="21" step="0.001">
			<options_item entry="r_mblur_power" group="mm_opt_video_adv"/>
		</track_r_cas_sharpening>

		<cap_r_cas_for_materials x="20" y="0" width="143" height="21">
			<text font="letterica16" r="215" g="195" b="170">ui_mm_r_cas_for_materials</text>
			<hint x="0" y="0" changeVisability="1">
				<text align="l" font="letterica16">ui_mm_r_cas_for_materials_hint</text>
				<hint_texture a="190" r="0" g="0" b="0">ui\ui_console</hint_texture>
				<text_color>
					<e r="0" g="0" b="0" a="0"/> 		<!-- Hidded -->
					<h r="215" g="195" b="170" a="160"/> 	<!-- Enabled -->
				</text_color>
			</hint>
		</cap_r_cas_for_materials>
		<check_r_cas_for_materials x="194" y="0" width="243" height="21">
			<options_item entry="r_cas_for_materials" group="mm_opt_video_adv"/>
			<hint x="0" y="0" changeVisability="1">
				<text align="l" font="letterica16">ui_mm_r_cas_for_materials_hint</text>
				<hint_texture a="190" r="0" g="0" b="0">ui\ui_console</hint_texture>
				<text_color>
					<e r="0" g="0" b="0" a="0"/> 		<!-- Hidded -->
					<h r="215" g="195" b="170" a="160"/> 	<!-- Enabled -->
				</text_color>
			</hint>
		</check_r_cas_for_materials>

		<cap_r_sun x="20" y="0" width="143" height="21">
			<text font="letterica16" r="215" g="195" b="170">ui_mm_r_sun</text>
		</cap_r_sun>
		<check_r_sun x="194" y="0" width="30" height="21">
			<options_item entry="r_sun" group="mm_opt_video"/>
		</check_r_sun>

		<cap_r_sun_quality x="20" y="0" width="143" height="21">
			<text font="letterica16" r="215" g="195" b="170">ui_mm_r_sun_quality</text>
		</cap_r_sun_quality>
		<list_r_sun_quality x="194" y="0" width="245" height="21" list_length="5">
			<options_item entry="r_sun_quality" group="mm_opt_video_adv"/>
			<text_color>
				<e r="216" g="186" b="140"/>
				<d r="227" g="199" b="178"/>
			</text_color>
			<list_font_s r="240" g="217" b="182"/>
			<list_font	 r="216" g="186" b="140" font="letterica16"/>
		</list_r_sun_quality>

		<cap_r_shadow_filtering x="20" y="0" width="143" height="21">
			<text font="letterica16" r="215" g="195" b="170">ui_mm_r_shadow_filtering</text>
		</cap_r_shadow_filtering>
		<list_r_shadow_filtering x="194" y="0" width="245" height="21" list_length="4">
			<options_item entry="r_shadow_filtering" group="mm_opt_video_adv"/>
			<text_color>
				<e r="216" g="186" b="140"/>
				<d r="227" g="199" b="178"/>
			</text_color>
			<list_font_s r="240" g="217" b="182"/>
			<list_font	 r="216" g="186" b="140" font="letterica16"/>
		</list_r_shadow_filtering>

		<cap_r_soft_water x="20" y="0" width="143" height="21">
			<text font="letterica16" r="215" g="195" b="170">ui_mm_r_soft_water</text>
			<hint x="0" y="0" changeVisability="1">
				<text align="l" font="letterica16">ui_mm_r_soft_water_hint</text>
				<hint_texture a="190" r="0" g="0" b="0">ui\ui_console</hint_texture>
				<text_color>
					<e r="0" g="0" b="0" a="0"/> 		<!-- Hidded -->
					<h r="215" g="195" b="170" a="160"/> 	<!-- Enabled -->
				</text_color>
			</hint>
		</cap_r_soft_water>
		<check_r_soft_water x="194" y="0" width="30" height="21">
			<options_item entry="r_soft_water" group="mm_opt_video_adv"/>
			<hint x="0" y="0" changeVisability="1">
				<text align="l" font="letterica16">ui_mm_r_soft_water_hint</text>
				<hint_texture a="190" r="0" g="0" b="0">ui\ui_console</hint_texture>
				<text_color>
					<e r="0" g="0" b="0" a="0"/> 		<!-- Hidded -->
					<h r="215" g="195" b="170" a="160"/> 	<!-- Enabled -->
				</text_color>
			</hint>
		</check_r_soft_water>

		<cap_r_soft_particles x="20" y="0" width="143" height="21">
			<text font="letterica16" r="215" g="195" b="170">ui_mm_r_soft_particles</text>
			<hint x="0" y="0" changeVisability="1">
				<text align="l" font="letterica16">ui_mm_r_soft_particles_hint</text>
				<hint_texture a="190" r="0" g="0" b="0">ui\ui_console</hint_texture>
				<text_color>
					<e r="0" g="0" b="0" a="0"/> 		<!-- Hidded -->
					<h r="215" g="195" b="170" a="160"/> 	<!-- Enabled -->
				</text_color>
			</hint>
		</cap_r_soft_particles>
		<check_r_soft_particles x="194" y="0" width="30" height="21">
			<options_item entry="r_soft_particles" group="mm_opt_video_adv"/>
			<hint x="0" y="0" changeVisability="1">
				<text align="l" font="letterica16">ui_mm_r_soft_particles_hint</text>
				<hint_texture a="190" r="0" g="0" b="0">ui\ui_console</hint_texture>
				<text_color>
					<e r="0" g="0" b="0" a="0"/> 		<!-- Hidded -->
					<h r="215" g="195" b="170" a="160"/> 	<!-- Enabled -->
				</text_color>
			</hint>
		</check_r_soft_particles>

		<cap_light_distance x="20" y="0" width="143" height="21">
			<text font="letterica16" r="215" g="195" b="170">ui_mm_light_distance</text>
		</cap_light_distance>
		<track_light_distance x="194" y="0" width="245" height="21">
			<options_item entry="r_slight_fade" group="mm_opt_video_adv_adv"/>
		</track_light_distance>
		
		<cap_npc_torch x="20" y="0" width="143" height="21">
			<text font="letterica16" r="215" g="195" b="170">ui_mm_npc_torch</text>
		</cap_npc_torch>
		<check_npc_torch x="194" y="0" width="243" height="21">
			<options_item entry="ai_use_torch_dynamic_lights" group="mm_opt_video_adv"/>
		</check_npc_torch>

		<cap_r_sun_details x="20" y="0" width="143" height="21">
			<text font="letterica16" r="215" g="195" b="170">ui_mm_r_sun_details</text>
		</cap_r_sun_details>
		<check_r_sun_details x="194" y="0" width="243" height="21">
			<options_item entry="r_sun_details" group="mm_opt_video_adv"/>
		</check_r_sun_details>

		<cap_r_material_quality x="20" y="0" width="143" height="21">
			<text font="letterica16" r="215" g="195" b="170">ui_mm_r_material_quality</text>
		</cap_r_material_quality>
		<list_r_material_quality x="194" y="0" width="245" height="21" list_length="4">
			<options_item entry="r_material_quality" group="mm_opt_video_adv"/>
			<text_color>
				<e r="216" g="186" b="140"/>
				<d r="227" g="199" b="178"/>
			</text_color>
			<list_font_s r="240" g="217" b="182"/>
			<list_font	 r="216" g="186" b="140" font="letterica16"/>
		</list_r_material_quality>

		<cap_particles_distance x="20" y="0" width="143" height="21">
			<text font="letterica16" r="215" g="195" b="170">ui_mm_particles_distance</text>
		</cap_particles_distance>
		<track_particles_distance x="194" y="0" width="245" height="21" step="0.1">
			<options_item entry="r_ls_squality" group="mm_opt_video_adv"/>
		</track_particles_distance>

		<cap_r_sun_shafts_enabled x="20" y="0" width="143" height="21">
			<text font="letterica16" r="215" g="195" b="170">ui_mm_r_sun_shafts_enabled</text>
			<hint x="0" y="0" changeVisability="1">
				<text align="l" font="letterica16">ui_mm_r_sun_shafts_enabled_hint</text>
				<hint_texture a="190" r="0" g="0" b="0">ui\ui_console</hint_texture>
				<text_color>
					<e r="0" g="0" b="0" a="0"/> 		<!-- Hidded -->
					<h r="215" g="195" b="170" a="160"/> 	<!-- Enabled -->
				</text_color>
			</hint>
		</cap_r_sun_shafts_enabled>
		<check_r_sun_shafts_enabled x="194" y="0" width="243" height="21">
			<options_item entry="r_sun_shafts_enabled" group="mm_opt_video_adv"/>
		</check_r_sun_shafts_enabled>

		<cap_r_sun_shafts_quality x="20" y="0" width="143" height="21">
			<text font="letterica16" r="215" g="195" b="170">ui_mm_r_sun_shafts_quality</text>
		</cap_r_sun_shafts_quality>
		<list_r_sun_shafts_quality x="194" y="0" width="245" height="21" list_length="3">
			<options_item entry="r_sun_shafts_quality" group="mm_opt_video_adv"/>
			<text_color>
				<e r="216" g="186" b="140"/>
				<d r="227" g="199" b="178"/>
			</text_color>
			<list_font_s r="240" g="217" b="182"/>
			<list_font	 r="216" g="186" b="140" font="letterica16"/>
		</list_r_sun_shafts_quality>

		<cap_r_ao_quality x="20" y="0" width="143" height="21">
			<text font="letterica16" r="215" g="195" b="170">ui_mm_r_ao_quality</text>
		</cap_r_ao_quality>
		<list_r_ao_quality x="194" y="0" width="245" height="21" list_length="2">
			<options_item entry="r_ao_quality" group="mm_opt_video_adv"/>
			<text_color>
				<e r="216" g="186" b="140"/>
				<d r="227" g="199" b="178"/>
			</text_color>
			<list_font_s r="240" g="217" b="182"/>
			<list_font	 r="216" g="186" b="140" font="letterica16"/>
		</list_r_ao_quality>

		<cap_r_rt_format x="20" y="0" width="143" height="21">
			<text font="letterica16" r="215" g="195" b="170">ui_mm_r_rt_format</text>
			<hint x="0" y="0" changeVisability="1">
				<text align="l" font="letterica16">ui_mm_r_rt_format_hint</text>
				<hint_texture a="190" r="0" g="0" b="0">ui\ui_console</hint_texture>
				<text_color>
					<e r="0" g="0" b="0" a="0"/> 		<!-- Hidded -->
					<h r="215" g="195" b="170" a="160"/> 	<!-- Enabled -->
				</text_color>
			</hint>
		</cap_r_rt_format>
		<list_r_rt_format x="194" y="0" width="245" height="21" list_length="2">
			<options_item entry="r_rt_format" group="mm_opt_video_adv"/>
			<text_color>
				<e r="216" g="186" b="140"/>
				<d r="227" g="199" b="178"/>
			</text_color>
			<list_font_s r="240" g="217" b="182"/>
			<list_font	 r="216" g="186" b="140" font="letterica16"/>
		</list_r_rt_format>

		<cap_r_autoexposure x="20" y="0" width="143" height="21">
			<text font="letterica16" r="215" g="195" b="170">ui_mm_r_autoexposure</text>
			<hint x="0" y="0" changeVisability="1">
				<text align="l" font="letterica16">ui_mm_r_autoexposure_hint</text>
				<hint_texture a="190" r="0" g="0" b="0">ui\ui_console</hint_texture>
				<text_color>
					<e r="0" g="0" b="0" a="0"/> 		<!-- Hidded -->
					<h r="215" g="195" b="170" a="160"/> 	<!-- Enabled -->
				</text_color>
			</hint>
		</cap_r_autoexposure>
		<check_r_autoexposure x="194" y="0" width="243" height="21">
			<options_item entry="r_autoexposure" group="mm_opt_video_adv"/>
			<hint x="0" y="0" changeVisability="1">
				<text align="l" font="letterica16">ui_mm_r_autoexposure_hint</text>
				<hint_texture a="190" r="0" g="0" b="0">ui\ui_console</hint_texture>
				<text_color>
					<e r="0" g="0" b="0" a="0"/> 		<!-- Hidded -->
					<h r="215" g="195" b="170" a="160"/> 	<!-- Enabled -->
				</text_color>
			</hint>
		</check_r_autoexposure>

		<cap_r_autoexposure_adaptation x="20" y="0" width="143" height="21">
			<text font="letterica16" r="215" g="195" b="170">ui_mm_r_autoexposure_adaptation</text>
			<hint x="0" y="0" changeVisability="1">
				<text align="l" font="letterica16">ui_mm_r_autoexposure_adaptation_hint</text>
				<hint_texture a="190" r="0" g="0" b="0">ui\ui_console</hint_texture>
				<text_color>
					<e r="0" g="0" b="0" a="0"/> 		<!-- Hidded -->
					<h r="215" g="195" b="170" a="160"/> 	<!-- Enabled -->
				</text_color>
			</hint>
		</cap_r_autoexposure_adaptation>
		<track_r_autoexposure_adaptation x="194" y="0" width="245" height="21" step="0.001">
			<options_item entry="r_autoexposure_adaptation" group="mm_opt_video_adv"/>
		</track_r_autoexposure_adaptation>

		<cap_r_sharpen x="20" y="0" width="143" height="21">
			<text font="letterica16" r="215" g="195" b="170">ui_mm_r_sharpen</text>
		</cap_r_sharpen>
		<check_r_sharpen x="194" y="0" width="243" height="21">
			<options_item entry="r_sharpen" group="mm_opt_video_adv"/>
		</check_r_sharpen>

		<cap_r_hdr x="20" y="0" width="143" height="21">
			<text font="letterica16" r="215" g="195" b="170">ui_mm_r_hdr</text>
			<hint x="0" y="0" changeVisability="1">
				<text align="l" font="letterica16">ui_mm_r_hdr_hint</text>
				<hint_texture a="190" r="0" g="0" b="0">ui\ui_console</hint_texture>
				<text_color>
					<e r="0" g="0" b="0" a="0"/> 		<!-- Hidded -->
					<h r="215" g="195" b="170" a="160"/> 	<!-- Enabled -->
				</text_color>
			</hint>
		</cap_r_hdr>
		<check_r_hdr x="194" y="0" width="243" height="21">
			<options_item entry="r_hdr" group="mm_opt_video_adv"/>
			<hint x="0" y="0" changeVisability="1">
				<text align="l" font="letterica16">ui_mm_r_hdr_hint</text>
				<hint_texture a="190" r="0" g="0" b="0">ui\ui_console</hint_texture>
				<text_color>
					<e r="0" g="0" b="0" a="0"/> 		<!-- Hidded -->
					<h r="215" g="195" b="170" a="160"/> 	<!-- Enabled -->
				</text_color>
			</hint>
		</check_r_hdr>

		<cap_r_hdr_brightness x="20" y="0" width="143" height="21">
			<text font="letterica16" r="215" g="195" b="170">ui_mm_r_hdr_brightness</text>
		</cap_r_hdr_brightness>
		<track_r_hdr_brightness x="194" y="0" width="245" height="21" step="0.001">
			<options_item entry="r_hdr_brightness" group="mm_opt_video_adv"/>
		</track_r_hdr_brightness>

		<cap_r_hdr_gamma x="20" y="0" width="143" height="21">
			<text font="letterica16" r="215" g="195" b="170">ui_mm_r_hdr_gamma</text>
		</cap_r_hdr_gamma>
		<track_r_hdr_gamma x="194" y="0" width="245" height="21" step="0.001">
			<options_item entry="r_hdr_gamma" group="mm_opt_video_adv"/>
		</track_r_hdr_gamma>

		<cap_60hz x="20" y="0" width="143" height="21">
			<text font="letterica16" r="215" g="195" b="170">ui_mm_60_hz</text>
			<hint x="0" y="0" changeVisability="1">
				<text align="l" font="letterica16">ui_mm_60_hz_hint</text>
				<hint_texture a="190" r="0" g="0" b="0">ui\ui_console</hint_texture>
				<text_color>
					<e r="0" g="0" b="0" a="0"/> 		<!-- Hidded -->
					<h r="215" g="195" b="170" a="160"/> 	<!-- Enabled -->
				</text_color>
			</hint>
		</cap_60hz>
		<check_60hz x="194" y="0" width="30" height="21">
			<options_item entry="rs_refresh_60hz" group="mm_opt_video_adv"/>
			<hint x="0" y="0" changeVisability="1">
				<text align="l" font="letterica16">ui_mm_60_hz_hint</text>
				<hint_texture a="190" r="0" g="0" b="0">ui\ui_console</hint_texture>
				<text_color>
					<e r="0" g="0" b="0" a="0"/> 		<!-- Hidded -->
					<h r="215" g="195" b="170" a="160"/> 	<!-- Enabled -->
				</text_color>
			</hint>
		</check_60hz>
		
		<btn_to_simply x="342" y="325" width="111" height="29">
			<text align="c" font="letterica16" r="227" g="199" b="178">ui_mm_simply</text>	
			<texture>ui_button_ordinary</texture>			
		</btn_to_simply>
	</video_adv>

	<tab_sound>
		<cap_mastervolume x="20" y="20" width="143" height="21">
			<text font="letterica16" r="215" g="195" b="170">ui_mm_master_volume</text>
		</cap_mastervolume>
		<track_mastervolume x="194" y="20" width="245" height="21" step="0.001">
			<options_item entry="snd_volume_master" group="mm_opt_sound"/>
		</track_mastervolume>

		<cap_effvolume x="20" y="45" width="143" height="21">
			<text font="letterica16" r="215" g="195" b="170">ui_mm_effects_volume</text>
		</cap_effvolume>
		<track_effvolume x="194" y="45" width="245" height="21" step="0.001">
			<options_item entry="snd_volume_eff" group="mm_opt_sound"/>
		</track_effvolume>

		<cap_musicvolume x="20" y="70" width="143" height="21">
			<text font="letterica16" r="215" g="195" b="170">ui_mm_music_volume</text>
		</cap_musicvolume>
		<track_musicvolume x="194" y="70" width="245" height="21" step="0.001">
			<options_item entry="snd_volume_music" group="mm_opt_sound"/>
		</track_musicvolume>

		<cap_weaponvolume x="20" y="95" width="143" height="21">
			<text font="letterica16" r="215" g="195" b="170">ui_mm_weapon_volume</text>
		</cap_weaponvolume>
		<track_weaponvolume x="194" y="95" width="245" height="21" step="0.001">
			<options_item entry="snd_volume_weapon_shooting" group="mm_opt_sound"/>
		</track_weaponvolume>

		<cap_ambientvolume x="20" y="120" width="143" height="21">
			<text font="letterica16" r="215" g="195" b="170">ui_mm_ambient_volume</text>
		</cap_ambientvolume>
		<track_ambientvolume x="194" y="120" width="245" height="21" step="0.001">
			<options_item entry="snd_volume_ambient" group="mm_opt_sound"/>
		</track_ambientvolume>

		<cap_snd_device x="20" y="145" width="143" height="21">
			<text font="letterica16" r="215" g="195" b="170">ui_mm_snd_device</text>
		</cap_snd_device>
		<list_snd_device x="194" y="145" width="245" height="21" always_show_scroll="1">
            		<options_item entry="snd_device" group="mm_opt_sound" depend="restart"/>
			<text_color>
				<e r="216" g="186" b="140"/>
				<d r="227" g="199" b="178"/>
			</text_color>
			<list_font_s r="240" g="217" b="182"/>
			<list_font	 r="216" g="186" b="140" font="letterica16"/>
		</list_snd_device>
		
		<check_eax x="20" y="170" width="143" height="21">
			<options_item entry="snd_efx" group="mm_opt_sound"/>
			<text font="letterica16" r="215" g="195" b="170">ui_mm_eax</text>
		</check_eax>		
		
		<btn_default_set x="342" y="325" width="111" height="29">
			<text align="c" font="letterica16" r="188" g="153" b="123">ui_mm_default</text>	
			<texture>ui_button_ordinary</texture>			
		</btn_default_set>
	</tab_sound>
	<tab_gameplay>
		<cap_difficulty x="20" y="20" width="143" height="21">
			<text font="letterica16" r="215" g="195" b="170">ui_mm_difficulty</text>
			<hint x="0" y="0" changeVisability="1">
				<text align="l" font="letterica16">ui_mm_difficulty_hint</text>
				<hint_texture a="190" r="0" g="0" b="0">ui\ui_console</hint_texture>
				<text_color>
					<e r="0" g="0" b="0" a="0"/> 		<!-- Hidded -->
					<h r="215" g="195" b="170" a="160"/> 	<!-- Enabled -->
				</text_color>
			</hint>			
		</cap_difficulty>

		<list_difficulty x="194" y="20" width="261" height="21" list_length="5">	
			<options_item entry="g_game_difficulty" group="mm_opt_gameplay"/>
			<text_color>
				<e r="216" g="186" b="140"/>
			</text_color>
			<list_font_s r="240" g="217" b="182"/>
			<list_font	 r="216" g="186" b="140" font="letterica16"/>
		</list_difficulty>
		
		<check_tips x="20" y="45" width="243" height="21">
			<options_item entry="hud_info" group="mm_opt_gameplay"/>
			<text font="letterica16" r="215" g="195" b="170">ui_mm_tips</text>
		</check_tips>
		<check_crosshair x="20" y="70" width="243" height="21">
			<options_item entry="hud_crosshair" group="mm_opt_gameplay"/>
			<text font="letterica16" r="215" g="195" b="170">ui_mm_show_crosshair</text>
		</check_crosshair>

		<check_dyn_crosshair x="20" y="95" width="243" height="21">
			<options_item entry="cl_dynamiccrosshair" group="mm_opt_gameplay"/>
			<text font="letterica16" r="215" g="195" b="170">ui_mm_dyn_crosshair</text>
		</check_dyn_crosshair>

		<check_show_weapon x="20" y="120" width="243" height="21">
			<options_item entry="hud_weapon" group="mm_opt_gameplay"/>
			<text font="letterica16" r="215" g="195" b="170">ui_mm_show_weapon</text>
		</check_show_weapon>

		<check_dist x="20" y="145" width="243" height="21">
			<options_item entry="hud_crosshair_dist" group="mm_opt_gameplay"/>
			<text font="letterica16" r="215" g="195" b="170">ui_mm_crosshair_distance</text>
		</check_dist>

		<check_hud_draw x="20" y="170" width="243" height="21">
			<options_item entry="hud_draw" group="mm_opt_gameplay"/>
			<text font="letterica16" r="215" g="195" b="170">ui_mm_hud_draw</text>
		</check_hud_draw>

		<check_view_bobbing_enable x="20" y="195" width="243" height="21">
			<options_item entry="view_bobbing_enable" group="mm_opt_gameplay"/>
			<text font="letterica16" r="215" g="195" b="170">ui_mm_view_bobbing_enable</text>
		</check_view_bobbing_enable>

		<check_weather_effects x="20" y="220" width="243" height="21">
			<options_item entry="weather_effects" group="mm_opt_gameplay"/>
			<text font="letterica16" r="215" g="195" b="170">ui_mm_weather_effects</text>
		</check_weather_effects>

		<check_cam_psp x="20" y="245" width="270" height="21">
			<options_item entry="cam_psp" group="mm_opt_gameplay"/>
			<text font="letterica16" r="215" g="195" b="170">ui_mm_cam_psp</text>
		</check_cam_psp>

		<check_game_intro_enable x="20" y="270" width="243" height="21">
			<options_item entry="game_intro_enable" group="mm_opt_gameplay"/>
			<text font="letterica16" r="215" g="195" b="170">ui_mm_game_intro_enable</text>
		</check_game_intro_enable>
		
	</tab_gameplay>
	<tab_controls>
		<cap_keyboardsetup x="6" y="95" width="456" height="23">
			<texture>ui_brokenline</texture>
			<text font="letterica16" r="215" g="195" b="170" x="10">ui_mm_keyboard_setup</text>
		</cap_keyboardsetup>

		<cap_mousesens x="20" y="15" width="150" height="21">
			<text font="letterica16" r="215" g="195" b="170">ui_mm_mouse_sense</text>
		</cap_mousesens>
		<track_mousesens x="194" y="15" width="261" height="21" step="0.01">
			<options_item entry="mouse_sens" group="mm_opt_controls"/>
		</track_mousesens>

		<cap_zoom_changing_type x="20" y="42" width="143" height="21">
			<text font="letterica16" r="215" g="195" b="170">ui_mm_zoom_changing_type</text>			
		</cap_zoom_changing_type>

		<list_zoom_changing_type x="194" y="40" width="261" height="21" list_length="2">	
			<options_item entry="wpn_zoom_button_mode" group="mm_opt_controls"/>
			<text_color>
				<e r="216" g="186" b="140"/>
			</text_color>
			<list_font_s r="240" g="217" b="182"/>
			<list_font	 r="216" g="186" b="140" font="letterica16"/>
		</list_zoom_changing_type>

		<check_mouseinvert x="20" y="65" width="143" height="21">
			<options_item entry="mouse_invert" group="mm_opt_controls"/>
			<text font="letterica16" r="215" g="195" b="170">ui_mm_invert_mouse</text>
		</check_mouseinvert>

		<key_binding x="10" y="120" width="451" height="199">
			<!-- headers -->
			<header_1 x="0" y="0" width="229" height="17">
				<text font="letterica16" r="215" g="195" b="170" x="2">ui_mm_action</text>
				<texture>ui_table_button_e</texture>
			</header_1>
			<header_2 x="229" y="0" width="102" height="17">
				<text font="letterica16" r="215" g="195" b="170" x="2">ui_mm_key</text>
				<texture>ui_table_button_e</texture>
			</header_2>
			<header_3 x="330" y="0" width="102" height="17">
				<text font="letterica16" r="215" g="195" b="170" x="2">ui_mm_alternative</text>
				<texture>ui_table_button_e</texture>
			</header_3>
			<!--frame-->
			<frame x="0" y="20" width="431" height="181">
				<texture>ui_cb_listbox</texture>
			</frame>
			<list x="0" y="20" width="451" height="181" item_height="18" always_show_scroll="1">
				<group_name font="letterica16" r="215" g="195" b="170"/>
				<item_text font="letterica16" r="215" g="215" b="215"/>				
			</list>
			
			<scroll_view x="0" y="20" width="447" height="181" always_show_scroll="1" vert_interval="3">
				<item_group x="0" y="0" width="160" height="25">
					<text font="letterica16" r="215" g="195" b="170"/>
				</item_group>
				
				<item_key x="0" y="0" width="414" height="18">
					<text font="letterica16" r="215" g="215" b="215"/>
				</item_key>
			</scroll_view>
		</key_binding>

		<btn_default x="342" y="325" width="111" height="29">
			<text align="c" font="letterica16" r="227" g="199" b="178">ui_mm_default</text>	
			<texture>ui_button_ordinary</texture>			
		</btn_default>
	</tab_controls>
	
	<frame x="0" y="0" width="470" height="330">
		<texture>ui_tablist_textbox</texture>		
	</frame>
	<frame_gameplay x="0" y="0" width="470" height="330">
		<texture>ui_tablist_textbox</texture>		
	</frame_gameplay>
	<frame_videoadv x="0" y="0" width="470" height="330">
		<texture>ui_tablist_textbox</texture>		
	</frame_videoadv>
	<download_static x="186" y="717" width="603" height="51">
		<texture>ui_patch_back</texture>
	</download_static>

	<download_text x="200" y="730" width="480" height="30">
		<text align="c" font="letterica16" r="135" g="123" b="116" complex_mode="0">mm_mp_progress</text>	
	</download_text>
	
	<progress_download x="222" y="754" width="403" height="10" horz="1" min="0" max="100">
		<progress>
			<texture>ui_patch_progress</texture>
		</progress>
	</progress_download>
	
	<btn_cancel_download x="652" y="732" width="111" height="29">
		<text align="c" font="letterica16" r="227" g="199" b="178">mm_mp_cancel</text>	
		<texture>ui_button_ordinary</texture>			
	</btn_cancel_download>
	
</window>
